Metadata-Version: 1.0
Name: xl-distributions
Version: 0.1
Summary: Gaussian distributions
Home-page: UNKNOWN
Author: Xiaolin Huang
Author-email: 501667014@qq.com
License: UNKNOWN
Platform: UNKNOWN
